lenny/__init__.py
lenny-0.1.2.dist-info/DESCRIPTION.rst
lenny-0.1.2.dist-info/METADATA
lenny-0.1.2.dist-info/RECORD
lenny-0.1.2.dist-info/WHEEL
lenny-0.1.2.dist-info/metadata.json
lenny-0.1.2.dist-info/top_level.txt
lenny-0.1.2.dist-info/zip-safe
