Metadata-Version: 2.0
Name: lenny
Version: 0.1.2
Summary: Generate random lenny faces.
Home-page: https://github.com/davidsluo/lenny
Author: davidsluo
Author-email: email@davidsluo.me
License: MIT
Keywords: lenny,face
Platform: UNKNOWN
